nlpviz/__init__.py
nlpviz/nlp_viz.py
nlpviz/test_nlp_viz.py
trulens_viz-0.0.2.dist-info/METADATA
trulens_viz-0.0.2.dist-info/WHEEL
trulens_viz-0.0.2.dist-info/top_level.txt
trulens_viz-0.0.2.dist-info/RECORD
