Metadata-Version: 2.1
Name: trulens-viz
Version: 0.0.2
Summary: Experimental NLP attribution strength visualization
Home-page: https://github.com/paepcke/trulens_viz.git
Author: Andreas Paepcke
Author-email: paepcke@cs.stanford.edu
License: UNKNOWN
Platform: UNKNOWN
Requires-Python: >=3.6
Requires-Dist: domonic (>=0.9.10)
Requires-Dist: matplotlib (>=3.5.1)
Requires-Dist: numpy (>=1.22.3)
Provides-Extra: test
Requires-Dist: nose2 (>=0.9.2) ; extra == 'test'
